{"target language": "Marquesan", "delimiters": [" ", ".", ",", ";", ":", "!", "?", "\u2026"], "pivot language": "English", "cq_uid": "1716852912", "data": {"1": {"legacy index": "1", "cq": "Have you ever seen pictures of my family?", "alternate_pivot": "", "translation": "e 'ite a'e nei 'oe te tau ata o to'u hua'a", "concept_words": {"ASK": "", "PROCESSIVE PREDICATE": "", "Ref_addressee": "'oe", "Ref_speaker": "to'u", "seeing": "'ite", "picture": "ata", "family": "hua'a"}, "comment": ""}, "2": {"legacy index": "2", "cq": "Well, I\u2019ve met some of your relatives, but I\u2019ve never seen your pictures.", "alternate_pivot": "", "translation": "ua tutuki a'e nei au i titahi tau hua'a o 'oe, a'e 'a au e 'ite a'e nei i ta 'oe tau ata", "concept_words": {"ASSERT": "", "PROCESSIVE PREDICATE": "", "Negative Polarity": "a'e_2", "Ref_speaker": "au", "Ref_addressee": "'oe_2", "meeting": "tutuki", "relatives": "hua'a", "BUT": "'a", "seeing": "'ite", "picture": "ata", "never": "a'e_2...a'e_3...nei_2"}, "comment": ""}, "3": {"legacy index": "3", "cq": "Here is an old photo album I just found in my parents\u2019 room.", "alternate_pivot": "", "translation": "'eia titahi kaputu ata kakiu ko'ana mai iau mei 'oto o te pa'oto o to'u p\u0101p\u0101 me to'u m\u0101m\u0101", "concept_words": {"ASSERT": "", "PRESENTATIVE PREDICATE": "", "PRESENT X": "'eia", "old": "kakiu", "photo album": "kaputu...ata", "Ref_speaker": "iau...to'u...to'u_2", "finding": "ko'ana", "parents": "p\u0101p\u0101...me...m\u0101m\u0101", "room": "pa'oto"}, "comment": ""}, "4": {"legacy index": "4", "cq": "Oh, show it to me please!", "alternate_pivot": "", "translation": "'a, a haka'ite mai a'e", "concept_words": {"ORDER": "a", "PROCESSIVE PREDICATE": "", "showing": "haka'ite", "Ref_speaker": "", "Ref_addressee": "", "Ref_1_object": ""}, "comment": ""}, "5": {"legacy index": "5", "cq": "Who\u2019s this on that first photo?", "alternate_pivot": "", "translation": "o ai te nei i 'uka o te ata tomua", "concept_words": {"ASK": "o...ai", "EQUATIVE PREDICATE": "", "PERSON wildcard": "o...ai", "POINTED BY SPEAKER": "te...nei", "photo": "ata", "first": "tomua", "equating": ""}, "comment": ""}, "6": {"legacy index": "6a", "cq": "It looks like olden times.", "alternate_pivot": "", "translation": "me he mea mea kakiu", "concept_words": {"EXPRESS LIKELIHOOD": "me...he", "PROCESSIVE PREDICATE": "", "looking like": "me...he", "olden times": "kakiu", "Ref_1_object": "mea"}, "comment": ""}, "7": {"legacy index": "6b", "cq": "It's in black and white.", "alternate_pivot": "", "translation": "mea ke'eke'e tava'i'e", "concept_words": {"ASSERT": "", "ATTRIBUTIVE PREDICATE": "mea", "exhibiting (an attribute)": "mea", "black and white": "ke'eke'e...tava'i'e", "Ref_1_object": ""}, "comment": ""}, "8": {"legacy index": "7a", "cq": "These are my grandparents, on my mother\u2019s side.", "alternate_pivot": "", "translation": "o to'u mou koko'oua i te k\u0113k\u0113 o to'u m\u0101m\u0101", "concept_words": {"ASSERT": "", "PRESENTATIVE PREDICATE": "o", "Ref_speaker": "to'u", "grandparents": "koko'oua", "mothers side": "k\u0113k\u0113...m\u0101m\u0101", "POINTED BY SPEAKER": "", "presenting (presentative)": "o"}, "comment": ""}, "9": {"legacy index": "7b", "cq": "Grandpa here on the left, and Grandma on the right.", "alternate_pivot": "", "translation": "ko'oua, 'inei i te 'ima a'ea'e, pakahio i te 'ima oko", "concept_words": {"ASSERT": "", "PRESENTATIVE PREDICATE": "", "POINTED BY SPEAKER": "'inei", "grandpa": "ko'oua", "left": "'ima...a'ea'e", "AND": "", "grandma": "pakahio", "right": "'ima_2...oko"}, "comment": ""}, "10": {"legacy index": "8", "cq": "The people around them must be their friends, or other relatives.", "alternate_pivot": "", "translation": "te po'i ma to 'aua kaokao o to 'aua tau hoa oti ako'e'a titahi tau hua'a", "concept_words": {"EXPRESS LIKELIHOOD": "", "EQUATIVE PREDICATE": "", "people": "po'i", "around": "kaokao", "friends": "hoa", "OR": "ako'e'a", "other": "titahi", "relatives": "hua'a", "Ref_2_people": "'aua", "equating": ""}, "comment": ""}, "11": {"legacy index": "9", "cq": "Was that the day of their wedding?", "alternate_pivot": "", "translation": "to 'aua '\u0101 matiri'ia tena", "concept_words": {"ASK": "", "EQUATIVE PREDICATE": "", "day": "'\u0101", "wedding": "matiri'ia", "equating": "", "Ref_Event": "", "Ref_2_people": "'aua"}, "comment": ""}, "12": {"legacy index": "10a", "cq": "No, I don\u2019t think so.", "alternate_pivot": "", "translation": "a'o'e, a'e oti", "concept_words": {"INFIRM": "a'o'e", "PROCESSIVE PREDICATE": "", "Negative Polarity": "a'o'e...a'e", "Ref_speaker": "", "thinking": "", "event wildcard": ""}, "comment": ""}, "13": {"legacy index": "10b", "cq": "They were older than this on their wedding. ", "alternate_pivot": "", "translation": "i to 'aua matiri'ia, mea 'ina ha'aoko a'e 'aua", "concept_words": {"ASSERT": "", "ATTRIBUTIVE PREDICATE": "mea", "Ref_2_people": "'aua", "OLDER THAN X": "ha'aoko...a'e", "wedding": "matiri'ia", "exhibiting (an attribute)": "mea", "Ref_1_object": ""}, "comment": ""}, "14": {"legacy index": "11", "cq": "This must have been the day when they got engaged.", "alternate_pivot": "", "translation": "o te '\u0101 ha'ana o to 'aua ha'ahei'ia", "concept_words": {"EXPRESS LIKELIHOOD": "", "PROCESSIVE PREDICATE": "", "equating": "", "Ref_Event": "", "day": "'\u0101", "getting engaged": "ha'ahei'ia", "Ref_2_people": "'aua"}, "comment": ""}, "15": {"legacy index": "12a", "cq": "In those times, the engagement was a major event for the whole family,", "alternate_pivot": "", "translation": "i te'a tai, mea taetae oko te ha'ahei'ia no te hua'a paotu", "concept_words": {"ASSERT": "", "EQUATIVE PREDICATE": "", "those times": "te'a...tai", "engagement": "ha'ahei'ia", "event_": "", "major": "taetae...oko", "family": "hua'a", "equating": ""}, "comment": ""}, "16": {"legacy index": "12b", "cq": "People would wear beautiful clothes.", "alternate_pivot": "", "translation": "e oka te 'enana i to 'atou kahu kanahau", "concept_words": {"ASSERT": "", "PROCESSIVE PREDICATE": "", "people": "'enana", "wearing": "oka", "beautiful": "kanahau", "clothes": "kahu"}, "comment": ""}, "17": {"legacy index": "13", "cq": "Have you met them?", "alternate_pivot": "", "translation": "ua 'ite 'oe ia 'aua", "concept_words": {"ASK": "", "PROCESSIVE PREDICATE": "", "meeting": "'ite", "Ref_addressee": "'oe", "Ref_2_people": "'aua"}, "comment": ""}, "18": {"legacy index": "14", "cq": "Who? My grandparents?", "alternate_pivot": "", "translation": "o ai ? to'u mou koko'oua", "concept_words": {"ASK": "o...ai", "PROCESSIVE PREDICATE": "", "PERSON wildcard": "o...ai", "grandparents": "koko'oua", "Ref_speaker": "to'u"}, "comment": ""}, "19": {"legacy index": "15", "cq": "Yes, your grandparents on the photo.", "alternate_pivot": "", "translation": "e, to 'oe mou koko'oua i 'uka o te ata", "concept_words": {"CONFIRM": "e", "PROCESSIVE PREDICATE": "", "grandparents": "koko'oua", "Ref_addressee": "'oe", "photo": "ata"}, "comment": ""}, "20": {"legacy index": "16a", "cq": "Actually no. ", "alternate_pivot": "", "translation": "a'o'e", "concept_words": {"INFIRM": "a'o'e"}, "comment": ""}, "21": {"legacy index": "16b", "cq": "They died before I was born.", "alternate_pivot": "", "translation": "ua mate 'aua ma mua to'u hanau", "concept_words": {"ASSERT": "", "PROCESSIVE PREDICATE": "", "Ref_2_people": "'aua", "dying": "mate", "BEFORE X": "ma...mua", "Ref_speaker": "to'u", "being born": "hanau"}, "comment": ""}, "22": {"legacy index": "16c", "cq": "They were born a long time ago.", "alternate_pivot": "", "translation": "mea 'oa 'aua te hanau'ia", "concept_words": {"ASSERT": "", "ATTRIBUTIVE PREDICATE": "mea", "Ref_2_people": "'aua", "being born": "hanau'ia", "_a long time ago": "mea...'oa"}, "comment": ""}, "23": {"legacy index": "17a", "cq": "Oh I see.", "alternate_pivot": "", "translation": "'a", "concept_words": {"SHOW ACTIVE LISTENING": ""}, "comment": ""}, "24": {"legacy index": "17b", "cq": "And who\u2019s that on the second photo?", "alternate_pivot": "", "translation": "o ai te nei i 'uka o te 'ua o te ata", "concept_words": {"ASK": "o...ai", "EQUATIVE PREDICATE": "", "PERSON wildcard": "o...ai", "second": "te_2...'ua", "photo": "ata", "POINTED BY SPEAKER": "te...nei", "equating": ""}, "comment": ""}, "25": {"legacy index": "18a", "cq": "This is my mother", "alternate_pivot": "", "translation": "o to'u kui", "concept_words": {"ASSERT": "", "EQUATIVE PREDICATE": "", "POINTED BY SPEAKER": "o", "mother": "kui", "Ref_speaker": "to'u", "equating": ""}, "comment": ""}, "26": {"legacy index": "18b", "cq": "when she was a child", "alternate_pivot": "", "translation": "na p\u014d to'iki o \u012ba", "concept_words": {"ASSERT": "", "EQUATIVE PREDICATE": "", "Ref_1_person": "\u012ba", "equating": "", "children": "to'iki", "time position wildcard": "na...p\u014d"}, "comment": ""}, "27": {"legacy index": "19a", "cq": "I guess she was coming back from school", "alternate_pivot": "", "translation": "ma'akau au e hua a'a \u012ba mei te ha'e hamani", "concept_words": {"EXPRESS LIKELIHOOD": "", "PROCESSIVE PREDICATE": "", "Ref_speaker": "au", "guessing": "ma'akau", "Ref_1_person": "\u012ba", "coming": "hua", "school": "ha'e...hamani"}, "comment": ""}, "28": {"legacy index": "19b", "cq": "look at her schoolbag.", "alternate_pivot": "", "translation": "ti'ohi 'ae i ta \u012ba kaka hamani", "concept_words": {"ORDER": "", "PROCESSIVE PREDICATE": "", "Ref_addressee": "", "looking": "ti'ohi", "schoolbag": "kaka...hamani", "Ref_1_person": "\u012ba"}, "comment": ""}, "29": {"legacy index": "", "cq": "Oh yeah, nice.", "alternate_pivot": "", "translation": "e", "concept_words": {"SHOW ACTIVE LISTENING": "", "APPRECIATIVE PREDICATE": ""}, "comment": ""}, "30": {"legacy index": "20", "cq": "And who is the small boy behind her?", "alternate_pivot": "", "translation": "o ai te kaiu maha'i i mu'i o \u012ba", "concept_words": {"ASK": "o...ai", "EQUATIVE PREDICATE": "", "PERSON wildcard": "o...ai", "small": "kaiu", "boy": "maha'i", "BEHIND X": "mu'i", "Ref_1_person": "\u012ba", "equating": ""}, "comment": ""}, "31": {"legacy index": "21a", "cq": "That\u2019s my uncle Teri.", "alternate_pivot": "", "translation": "o to'u toto teri", "concept_words": {"ASSERT": "", "EQUATIVE PREDICATE": "", "uncle": "toto", "Teri": "teri", "equating": "", "POINTED BY SPEAKER": "o", "Ref_speaker": "to'u"}, "comment": ""}, "32": {"legacy index": "21b", "cq": "You\u2019ve never met him.", "alternate_pivot": "", "translation": "a'e 'oe e 'ite a'e nei ia \u012ba", "concept_words": {"ASSERT": "", "PROCESSIVE PREDICATE": "", "Negative Polarity": "a'e", "Ref_addressee": "'oe", "never": "a'e...a'e_2...nei", "meeting": "'ite", "Ref_1_person": "\u012ba"}, "comment": ""}, "33": {"legacy index": "21c", "cq": "He lives far away from here.", "alternate_pivot": "", "translation": "mea mamao to \u012ba noho mei 'inei", "concept_words": {"ASSERT": "", "PROCESSIVE PREDICATE": "", "Ref_1_person": "\u012ba", "residing": "noho", "far away": "mamao", "here": "'inei"}, "comment": ""}, "34": {"legacy index": "22", "cq": "And what school did they attend then?", "alternate_pivot": "", "translation": "i hea to 'aua ha'e hamani e he'e nei", "concept_words": {"ASK": "", "ATTRIBUTIVE PREDICATE": "", "attending": "he'e", "Ref_2_people": "'aua", "school": "ha'e...hamani", "object wildcard": "", "then (time)": ""}, "comment": ""}, "35": {"legacy index": "23", "cq": "That was an old school that doesn\u2019t exist anymore.", "alternate_pivot": "", "translation": "e ha'e hamani kakiu, ahe mea haka'ua", "concept_words": {"ASSERT": "", "EQUATIVE PREDICATE": "", "Negative Polarity": "", "existing": "", "equating": "", "Ref_1_object": "e", "old": "kakiu", "school": "ha'e...hamani", "anymore": "ahe...mea...haka'ua"}, "comment": ""}, "36": {"legacy index": "23", "cq": "It was located down the road, towards the lake.", "alternate_pivot": "", "translation": "ma 'a'o o te va'anui, i te taha ka'avai", "concept_words": {"ASSERT": "", "LOCATIVE PREDICATE": "ma", "AND": "", "down the road": "ma...'a'o...o...te...va'anui", "TOWARD X": "te_2...taha", "lake": "", "BEING LOCATED": "", "Ref_1_object": ""}, "comment": ""}, "37": {"legacy index": "24", "cq": "Let me see this other photo.", "alternate_pivot": "", "translation": "'aia'e titahi atana", "concept_words": {"ORDER": "'aia'e", "PROCESSIVE PREDICATE": "", "Ref_addressee": "", "allowing": "", "Ref_speaker": "", "seeing": "", "OTHER X": "titahi", "picture": "atana", "POINTED BY SPEAKER": "atana"}, "comment": ""}, "38": {"legacy index": "25", "cq": "This woman is surely your mother again, carrying a child on her back.", "alternate_pivot": "", "translation": "te nei vehine, o to 'oe kui toitoi haka'ua tena e amo a'a te tama io he vi'itua", "concept_words": {"EQUATIVE PREDICATE": "", "PROCESSIVE PREDICATE": "", "women": "vehine", "POINTED BY SPEAKER": "te...nei", "surely": "toitoi", "mother": "kui", "Ref_addressee": "'oe", "again": "haka'ua", "carrying": "amo", "children": "tama", "back (anatomy)": "vi'itua", "Ref_1_person": "", "equating": ""}, "comment": ""}, "39": {"legacy index": "26a", "cq": "Oh, I think I know who this child is.", "alternate_pivot": "", "translation": "eo, ua 'ite oti au o ai te nei tama", "concept_words": {"EXPRESS BELIEF (EPISTEMIC)": "", "PROCESSIVE PREDICATE": "", "EQUATIVE PREDICATE": "", "Ref_speaker": "au", "thinking": "oti", "knowing": "'ite", "PERSON wildcard": "o...ai", "children": "tama", "POINTED BY SPEAKER": "te...nei", "equating": ""}, "comment": ""}, "40": {"legacy index": "26b", "cq": "That\u2019s you!", "alternate_pivot": "", "translation": "o 'oe", "concept_words": {"ASSERT": "", "EQUATIVE PREDICATE": "", "POINTED BY SPEAKER": "o", "Ref_addressee": "'oe", "equating": ""}, "comment": ""}, "41": {"legacy index": "27a", "cq": "That's me indeed!", "alternate_pivot": "", "translation": "tena", "concept_words": {"CONFIRM": "tena", "EQUATIVE PREDICATE": "", "POINTED BY SPEAKER": "", "Ref_speaker": "", "equating": ""}, "comment": ""}, "42": {"legacy index": "27b", "cq": "How did you recognize me?", "alternate_pivot": "", "translation": "pehea to 'oe 'itea", "concept_words": {"ASK": "pehea", "PROCESSIVE PREDICATE": "", "Ref_addressee": "'oe", "recognizing": "'itea", "Ref_speaker": "", "process wildcard": ""}, "comment": ""}, "43": {"legacy index": "28a", "cq": "Well, on that photo you\u2019re a small child,", "alternate_pivot": "", "translation": "e kai\u016b to'iki 'oe i 'uka o tena ata", "concept_words": {"ASSERT": "", "ATTRIBUTIVE PREDICATE": "", "Ref_addressee": "'oe", "small": "kai\u016b", "children": "to'iki", "photo": "ata", "POINTED BY SPEAKER": "tena", "exhibiting (an attribute)": "e"}, "comment": ""}, "44": {"legacy index": "28b", "cq": "but I recognize your eyes and your smile.", "alternate_pivot": "", "translation": "atika 'a ua 'ite au i to 'oe mata me to 'oe mata katakata", "concept_words": {"ASSERT": "", "PROCESSIVE PREDICATE": "", "BUT": "atika...'a", "recognizing": "'ite", "Ref_speaker": "au", "Ref_addressee": "'oe", "eyes": "mata", "AND": "me", "smile": "mata_2...katakata"}, "comment": ""}, "45": {"legacy index": "29", "cq": "You look mischievous on that picture.", "alternate_pivot": "", "translation": "ia ti'ohi au tenei ata, mea keu 'oe", "concept_words": {"ASSERT": "", "PROCESSIVE PREDICATE": "", "Ref_addressee": "'oe", "looking like": "", "mischievous": "keu", "picture": "ata", "POINTED BY SPEAKER": "tenei"}, "comment": ""}, "46": {"legacy index": "30", "cq": "You haven\u2019t changed much!", "alternate_pivot": "", "translation": "a'i taui oko 'oe", "concept_words": {"ASSERT": "", "PROCESSIVE PREDICATE": "", "Negative Polarity": "a'i", "Ref_addressee": "'oe", "changing (over time)": "taui", "much": "oko"}, "comment": ""}, "47": {"legacy index": "31a", "cq": "Ha ha.", "alternate_pivot": "", "translation": "ha ha", "concept_words": {"SHOW ACTIVE LISTENING": ""}, "comment": ""}, "48": {"legacy index": "31b", "cq": "But I\u2019m not a child any more, I\u2019ve grown up.", "alternate_pivot": "", "translation": "atika 'a, a'e au e to'iki haka'ua, ua ka'uo'o au", "concept_words": {"ASSERT": "", "EQUATIVE PREDICATE": "", "PROCESSIVE PREDICATE": "", "Negative Polarity": "a'e", "BUT": "atika...'a", "AND": "", "Ref_speaker": "au", "children": "to'iki", "anymore": "a'e...haka'ua", "growing up": "ka'uo'o", "equating": ""}, "comment": ""}, "49": {"legacy index": "32", "cq": "Today my mother would not be able to carry me on her back!", "alternate_pivot": "", "translation": "tenei, a'e au e 'i'o haka'ua i to'u kui ia amo", "concept_words": {"ASSERT": "", "PROCESSIVE PREDICATE": "", "Negative Polarity": "a'e", "today": "tenei", "mother": "kui", "Ref_speaker": "au", "being able to": "", "carrying": "'i'o", "back (anatomy)": "", "Ref_1_person": ""}, "comment": ""}, "50": {"legacy index": "33", "cq": "I\u2019m taller and heavier than her.", "alternate_pivot": "", "translation": "mea 'oa, mea toko a'e au ia \u012ba", "concept_words": {"ASSERT": "", "PROCESSIVE PREDICATE": "", "Ref_speaker": "au", "MORE X THAN Y": "mea...a'e...ia", "AND": "", "tall": "'oa", "heavy": "toko", "Ref_1_person": "\u012ba", "exhibiting (an attribute)": "mea"}, "comment": ""}, "51": {"legacy index": "34a", "cq": "Ha, that\u2019s true.", "alternate_pivot": "", "translation": "e, toitoi", "concept_words": {"CONFIRM": "e", "APPRECIATIVE PREDICATE": ""}, "comment": ""}}, "interviewer": "Marie TEIKITOHE", "interviewee": "Marie TEIKITOHE", "recording_uid": "1731208706", "owner name": "Marie Tearere Teikitohe Curieux", "owner orcid": "", "authorization": "accessed read-only by anyone via DIG4EL tools"}